tsregressor/__init__.py
tsregressor/models.py
tsregressor-0.1.0.dist-info/METADATA
tsregressor-0.1.0.dist-info/WHEEL
tsregressor-0.1.0.dist-info/top_level.txt
tsregressor-0.1.0.dist-info/RECORD
